etrsitrs/__init__.py
etrsitrs/datumtransformation.py
etrsitrs/main.py
etrsitrs/parameterset.py
etrs_itrs-0.1.dist-info/LICENSE
etrs_itrs-0.1.dist-info/METADATA
etrs_itrs-0.1.dist-info/WHEEL
etrs_itrs-0.1.dist-info/top_level.txt
etrs_itrs-0.1.dist-info/RECORD
