Metadata-Version: 2.1
Name: etrs-itrs
Version: 0.1
Summary: A python tool to convert ETRS to ITRF coordinates.
Home-page: https://github.com/brentjens/etrs-itrs
Author: Michiel Brentjens
Author-email: brentjens@astron.nl
License: Apache License 2.0
Classifier: Development Status :: 3 - Alpha
Classifier: Environment :: No Input/Output (Daemon)
Classifier: Intended Audience :: Developers
Classifier: Intended Audience :: Science/Research
Classifier: License :: OSI Approved :: Apache Software License
Classifier: Operating System :: OS Independent
Classifier: Programming Language :: Python
Classifier: Programming Language :: Python :: 3
Classifier: Programming Language :: Python :: 3 :: Only
Classifier: Programming Language :: Python :: 3.6
Classifier: Programming Language :: Python :: 3.7
Classifier: Programming Language :: Python :: 3.8
Classifier: Programming Language :: Python :: 3.9
Classifier: Programming Language :: Python :: 3.10
Classifier: Programming Language :: Python :: 3.11
Classifier: Topic :: Scientific/Engineering
Classifier: Topic :: Scientific/Engineering :: Astronomy
Requires-Python: >=3.6
License-File: LICENSE
Requires-Dist: numpy
Requires-Dist: importlib-metadata >=0.12 ; python_version < "3.8"
